datavice/__about__.py
datavice/__init__.py
datavice-0.0.1.dist-info/METADATA
datavice-0.0.1.dist-info/WHEEL
datavice-0.0.1.dist-info/licenses/LICENSE.txt
datavice-0.0.1.dist-info/RECORD
