Metadata-Version: 2.4
Name: datavice
Version: 0.0.1
Summary: DATAVICE official API (name occupy package)
Project-URL: Documentation, https://github.com/DATAVICEhost/datavice-python#readme
Project-URL: Issues, https://github.com/DATAVICEhost/datavice-python/issues
Project-URL: Source, https://github.com/DATAVICEhost/datavice-python
Author-email: marat2509 <marat2509@users.noreply.github.com>
License-Expression: MIT
License-File: LICENSE.txt
Classifier: Development Status :: 4 - Beta
Classifier: Programming Language :: Python
Classifier: Programming Language :: Python :: 3.8
Classifier: Programming Language :: Python :: 3.9
Classifier: Programming Language :: Python :: 3.10
Classifier: Programming Language :: Python :: 3.11
Classifier: Programming Language :: Python :: 3.12
Classifier: Programming Language :: Python :: Implementation :: CPython
Classifier: Programming Language :: Python :: Implementation :: PyPy
Requires-Python: >=3.8
